odoo8_addon_partner_identification-8.0.1.1.1.99.dev9-py3.8-nspkg.pth
odoo_addons/partner_identification/README.rst
odoo_addons/partner_identification/__init__.py
odoo_addons/partner_identification/__openerp__.py
odoo_addons/partner_identification/i18n/de.po
odoo_addons/partner_identification/i18n/es.po
odoo_addons/partner_identification/i18n/eu.po
odoo_addons/partner_identification/i18n/fr.po
odoo_addons/partner_identification/i18n/it.po
odoo_addons/partner_identification/i18n/partner_identification.pot
odoo_addons/partner_identification/i18n/sl.po
odoo_addons/partner_identification/models/__init__.py
odoo_addons/partner_identification/models/res_partner.py
odoo_addons/partner_identification/models/res_partner_id_category.py
odoo_addons/partner_identification/models/res_partner_id_number.py
odoo_addons/partner_identification/security/ir.model.access.csv
odoo_addons/partner_identification/static/description/icon.png
odoo_addons/partner_identification/tests/__init__.py
odoo_addons/partner_identification/tests/test_partner_identification.py
odoo_addons/partner_identification/tests/test_res_partner.py
odoo_addons/partner_identification/views/res_partner_id_category_view.xml
odoo_addons/partner_identification/views/res_partner_id_number_view.xml
odoo_addons/partner_identification/views/res_partner_view.xml
odoo8_addon_partner_identification-8.0.1.1.1.99.dev9.dist-info/METADATA
odoo8_addon_partner_identification-8.0.1.1.1.99.dev9.dist-info/WHEEL
odoo8_addon_partner_identification-8.0.1.1.1.99.dev9.dist-info/namespace_packages.txt
odoo8_addon_partner_identification-8.0.1.1.1.99.dev9.dist-info/top_level.txt
odoo8_addon_partner_identification-8.0.1.1.1.99.dev9.dist-info/RECORD
